LICENSE.txt
MANIFEST.in
README.md
setup.py
flask_simple_captcha/__init__.py
flask_simple_captcha/arial.ttf
flask_simple_captcha/config.py
flask_simple_captcha_r.egg-info/PKG-INFO
flask_simple_captcha_r.egg-info/SOURCES.txt
flask_simple_captcha_r.egg-info/dependency_links.txt
flask_simple_captcha_r.egg-info/requires.txt
flask_simple_captcha_r.egg-info/top_level.txt