Metadata-Version: 2.1
Name: flask-simple-captcha-r
Version: 1.1.0
Summary: Extremely simple, "Good Enough" captcha implemention for flask forms. No server side sessions required.
Home-page: https://github.com/cc-d/flask-simple-captcha
Author: Kefuphblu
Author-email: opqwerty20@yandex.ru
License: MIT
Platform: UNKNOWN
Classifier: License :: OSI Approved :: MIT License
Classifier: Programming Language :: Python :: 3
Classifier: Programming Language :: Python :: 3.7
License-File: LICENSE.txt
